QukuaiLianJishuKuaisuRumenjiaochengCYuyanZhongwenwang/README.md
QukuaiLianJishuKuaisuRumenjiaochengCYuyanZhongwenwang/__init__.py
QukuaiLianJishuKuaisuRumenjiaochengCYuyanZhongwenwang/__main__.py
QukuaiLianJishuKuaisuRumenjiaochengCYuyanZhongwenwang/file.epub
QukuaiLianJishuKuaisuRumenjiaochengCYuyanZhongwenwang/index.html
QukuaiLianJishuKuaisuRumenjiaochengCYuyanZhongwenwang/css/__init__.py
QukuaiLianJishuKuaisuRumenjiaochengCYuyanZhongwenwang/css/annotations.css
QukuaiLianJishuKuaisuRumenjiaochengCYuyanZhongwenwang/css/main.css
QukuaiLianJishuKuaisuRumenjiaochengCYuyanZhongwenwang/css/normalize.css
QukuaiLianJishuKuaisuRumenjiaochengCYuyanZhongwenwang/css/popup.css
QukuaiLianJishuKuaisuRumenjiaochengCYuyanZhongwenwang/font/__init__.py
QukuaiLianJishuKuaisuRumenjiaochengCYuyanZhongwenwang/font/fontello.eot
QukuaiLianJishuKuaisuRumenjiaochengCYuyanZhongwenwang/font/fontello.svg
QukuaiLianJishuKuaisuRumenjiaochengCYuyanZhongwenwang/font/fontello.ttf
QukuaiLianJishuKuaisuRumenjiaochengCYuyanZhongwenwang/font/fontello.woff
QukuaiLianJishuKuaisuRumenjiaochengCYuyanZhongwenwang/img/__init__.py
QukuaiLianJishuKuaisuRumenjiaochengCYuyanZhongwenwang/img/annotator-glyph-sprite.png
QukuaiLianJishuKuaisuRumenjiaochengCYuyanZhongwenwang/img/annotator-icon-sprite.png
QukuaiLianJishuKuaisuRumenjiaochengCYuyanZhongwenwang/img/apple-touch-icon.png
QukuaiLianJishuKuaisuRumenjiaochengCYuyanZhongwenwang/img/cancelfullscreen.png
QukuaiLianJishuKuaisuRumenjiaochengCYuyanZhongwenwang/img/close.png
QukuaiLianJishuKuaisuRumenjiaochengCYuyanZhongwenwang/img/fullscreen.png
QukuaiLianJishuKuaisuRumenjiaochengCYuyanZhongwenwang/img/loader.gif
QukuaiLianJishuKuaisuRumenjiaochengCYuyanZhongwenwang/img/menu-icon.png
QukuaiLianJishuKuaisuRumenjiaochengCYuyanZhongwenwang/img/save.png
QukuaiLianJishuKuaisuRumenjiaochengCYuyanZhongwenwang/img/saved.png
QukuaiLianJishuKuaisuRumenjiaochengCYuyanZhongwenwang/img/settings-s.png
QukuaiLianJishuKuaisuRumenjiaochengCYuyanZhongwenwang/img/settings.png
qukuai_lian_jishu_kuaisu_rumenjiaocheng_c_yuyan_zhongwenwang-2024.3.4.0.dist-info/METADATA
qukuai_lian_jishu_kuaisu_rumenjiaocheng_c_yuyan_zhongwenwang-2024.3.4.0.dist-info/WHEEL
qukuai_lian_jishu_kuaisu_rumenjiaocheng_c_yuyan_zhongwenwang-2024.3.4.0.dist-info/entry_points.txt
qukuai_lian_jishu_kuaisu_rumenjiaocheng_c_yuyan_zhongwenwang-2024.3.4.0.dist-info/top_level.txt
qukuai_lian_jishu_kuaisu_rumenjiaocheng_c_yuyan_zhongwenwang-2024.3.4.0.dist-info/RECORD
